compression_prompt/__init__.py
compression_prompt/cli.py
compression_prompt/compressor.py
compression_prompt/image_renderer.py
compression_prompt/py.typed
compression_prompt/quality_metrics.py
compression_prompt/statistical_filter.py
compression_prompt-0.1.2.dist-info/licenses/LICENSE
compression_prompt-0.1.2.dist-info/METADATA
compression_prompt-0.1.2.dist-info/WHEEL
compression_prompt-0.1.2.dist-info/entry_points.txt
compression_prompt-0.1.2.dist-info/top_level.txt
compression_prompt-0.1.2.dist-info/RECORD
