Metadata-Version: 2.4
Name: compression_prompt
Version: 0.1.2
Summary: Fast statistical compression for LLM prompts - 50% token reduction with 91% quality retention
Home-page: https://github.com/hivellm/compression-prompt
Author: HiveLLM Team
Author-email: HiveLLM Team <team@hivellm.org>
Project-URL: Homepage, https://github.com/hivellm/compression-prompt
Project-URL: Repository, https://github.com/hivellm/compression-prompt
Project-URL: Bug Reports, https://github.com/hivellm/compression-prompt/issues
Project-URL: Documentation, https://github.com/hivellm/compression-prompt/blob/main/README.md
Keywords: llm,compression,prompt,optimization,token-reduction,nlp,ai
Classifier: Development Status :: 4 - Beta
Classifier: Intended Audience :: Developers
Classifier: Topic :: Text Processing
Classifier: Topic :: Scientific/Engineering :: Artificial Intelligence
Classifier: Programming Language :: Python :: 3
Classifier: Programming Language :: Python :: 3.8
Classifier: Programming Language :: Python :: 3.9
Classifier: Programming Language :: Python :: 3.10
Classifier: Programming Language :: Python :: 3.11
Classifier: Programming Language :: Python :: 3.12
Classifier: Operating System :: OS Independent
Requires-Python: >=3.8
License-File: LICENSE
Provides-Extra: dev
Requires-Dist: pytest>=7.0.0; extra == "dev"
Requires-Dist: pytest-cov>=4.0.0; extra == "dev"
Requires-Dist: black>=23.0.0; extra == "dev"
Requires-Dist: mypy>=1.0.0; extra == "dev"
Requires-Dist: ruff>=0.1.0; extra == "dev"
Requires-Dist: build>=0.10.0; extra == "dev"
Requires-Dist: twine>=4.0.0; extra == "dev"
Provides-Extra: image
Requires-Dist: Pillow>=10.0.0; extra == "image"
Provides-Extra: all
Requires-Dist: Pillow>=10.0.0; extra == "all"
Dynamic: author
Dynamic: home-page
Dynamic: license-file
Dynamic: requires-python
